anchorbrowser/__init__.py
anchorbrowser/_base_client.py
anchorbrowser/_client.py
anchorbrowser/_compat.py
anchorbrowser/_constants.py
anchorbrowser/_exceptions.py
anchorbrowser/_files.py
anchorbrowser/_models.py
anchorbrowser/_qs.py
anchorbrowser/_resource.py
anchorbrowser/_response.py
anchorbrowser/_streaming.py
anchorbrowser/_types.py
anchorbrowser/_version.py
anchorbrowser/py.typed
anchorbrowser/_utils/__init__.py
anchorbrowser/_utils/_compat.py
anchorbrowser/_utils/_datetime_parse.py
anchorbrowser/_utils/_logs.py
anchorbrowser/_utils/_proxy.py
anchorbrowser/_utils/_reflection.py
anchorbrowser/_utils/_resources_proxy.py
anchorbrowser/_utils/_streams.py
anchorbrowser/_utils/_sync.py
anchorbrowser/_utils/_transform.py
anchorbrowser/_utils/_typing.py
anchorbrowser/_utils/_utils.py
anchorbrowser/lib/.keep
anchorbrowser/lib/agent.py
anchorbrowser/lib/browser.py
anchorbrowser/resources/__init__.py
anchorbrowser/resources/agent.py
anchorbrowser/resources/browser.py
anchorbrowser/resources/events.py
anchorbrowser/resources/extensions.py
anchorbrowser/resources/identities.py
anchorbrowser/resources/profiles.py
anchorbrowser/resources/task.py
anchorbrowser/resources/tools.py
anchorbrowser/resources/applications/__init__.py
anchorbrowser/resources/applications/applications.py
anchorbrowser/resources/applications/auth_flows.py
anchorbrowser/resources/sessions/__init__.py
anchorbrowser/resources/sessions/all.py
anchorbrowser/resources/sessions/clipboard.py
anchorbrowser/resources/sessions/keyboard.py
anchorbrowser/resources/sessions/mouse.py
anchorbrowser/resources/sessions/sessions.py
anchorbrowser/resources/sessions/agent/__init__.py
anchorbrowser/resources/sessions/agent/agent.py
anchorbrowser/resources/sessions/agent/files.py
anchorbrowser/resources/sessions/recordings/__init__.py
anchorbrowser/resources/sessions/recordings/primary.py
anchorbrowser/resources/sessions/recordings/recordings.py
anchorbrowser/types/__init__.py
anchorbrowser-0.7.4.dist-info/METADATA
anchorbrowser-0.7.4.dist-info/WHEEL
anchorbrowser-0.7.4.dist-info/licenses/LICENSE
anchorbrowser-0.7.4.dist-info/RECORD
